{
  "auditLogs": [
    { "id": "log-1", "time": "2026-05-31 09:32", "operator": "老夏", "module": "设置中心", "object": "角色权限", "action": "修改数据权限", "result": "成功", "ip": "10.10.1.23" },
    { "id": "log-2", "time": "2026-05-31 09:18", "operator": "系统任务", "module": "日志与数据", "object": "数据备份", "action": "执行增量备份", "result": "成功", "ip": "127.0.0.1" },
    { "id": "log-3", "time": "2026-05-30 18:04", "operator": "李文涛", "module": "采购中心", "object": "采购订单", "action": "导出列表", "result": "成功", "ip": "10.10.2.18" }
  ],
  "tasks": [
    { "id": "BAK-20260531-001", "type": "数据备份", "scope": "业务数据 / 附件 / 系统参数", "time": "2026-05-31 02:00", "amount": "18.6 GB", "status": "成功" },
    { "id": "IMP-20260530-006", "type": "导入任务", "scope": "客户主数据", "time": "2026-05-30 16:20", "amount": "2,480 行", "status": "完成" },
    { "id": "EXP-20260530-012", "type": "导出记录", "scope": "操作日志", "time": "2026-05-30 15:08", "amount": "156 条", "status": "完成" }
  ]
}
